func_assistant/__init__.py
func_assistant/main.py
func_assistant/start.py
func_assistant-0.1.5.dist-info/entry_points.txt
func_assistant-0.1.5.dist-info/LICENSE
func_assistant-0.1.5.dist-info/WHEEL
func_assistant-0.1.5.dist-info/METADATA
func_assistant-0.1.5.dist-info/RECORD
