Metadata-Version: 2.1
Name: func_assistant
Version: 0.1.5
Summary: my cool axx package
Author-email: RobertCodedIt <robertlove999999@gmail.com>
Classifier: License :: OSI Approved :: MIT License
Project-URL: Home, https://github.com/robertCodedIt/misc-pkg
